ix_cli/__init__.py
ix_cli/cli.py
ix_cli/utils.py
ix_cli-0.1.3.dist-info/LICENSE
ix_cli-0.1.3.dist-info/METADATA
ix_cli-0.1.3.dist-info/WHEEL
ix_cli-0.1.3.dist-info/entry_points.txt
ix_cli-0.1.3.dist-info/RECORD
