Metadata-Version: 2.1
Name: ix-cli
Version: 0.1.3
Summary: 
Home-page: https://github.com/arnos-stuff/ix
License: MIT
Author: arnos-stuff
Author-email: bcda0276@gmail.com
Requires-Python: >=3.9,<4.0
Classifier: License :: OSI Approved :: MIT License
Classifier: Programming Language :: Python :: 3
Classifier: Programming Language :: Python :: 3.9
Classifier: Programming Language :: Python :: 3.10
Classifier: Programming Language :: Python :: 3.11
Requires-Dist: requests (>=2.28.2,<3.0.0)
Requires-Dist: typer[all] (>=0.7.0,<0.8.0) ; python_version < "3.11"
Requires-Dist: typer[all] (>=0.9.0) ; python_version >= "3.11"
